graflo/README.md
graflo/__init__.py
graflo/caster.py
graflo/logging.conf
graflo/onto.py
graflo/architecture/__init__.py
graflo/architecture/actor.py
graflo/architecture/actor_util.py
graflo/architecture/edge.py
graflo/architecture/onto.py
graflo/architecture/onto_sql.py
graflo/architecture/resource.py
graflo/architecture/schema.py
graflo/architecture/transform.py
graflo/architecture/util.py
graflo/architecture/vertex.py
graflo/cli/__init__.py
graflo/cli/ingest.py
graflo/cli/manage_dbs.py
graflo/cli/plot_schema.py
graflo/cli/xml2json.py
graflo/data_source/__init__.py
graflo/data_source/api.py
graflo/data_source/base.py
graflo/data_source/factory.py
graflo/data_source/file.py
graflo/data_source/memory.py
graflo/data_source/registry.py
graflo/data_source/sql.py
graflo/db/__init__.py
graflo/db/conn.py
graflo/db/manager.py
graflo/db/util.py
graflo/db/arango/__init__.py
graflo/db/arango/conn.py
graflo/db/arango/query.py
graflo/db/arango/util.py
graflo/db/connection/__init__.py
graflo/db/connection/config_mapping.py
graflo/db/connection/onto.py
graflo/db/connection/wsgi.py
graflo/db/falkordb/__init__.py
graflo/db/falkordb/conn.py
graflo/db/memgraph/__init__.py
graflo/db/memgraph/conn.py
graflo/db/neo4j/__init__.py
graflo/db/neo4j/conn.py
graflo/db/postgres/__init__.py
graflo/db/postgres/conn.py
graflo/db/postgres/fuzzy_matcher.py
graflo/db/postgres/heuristics.py
graflo/db/postgres/inference_utils.py
graflo/db/postgres/resource_mapping.py
graflo/db/postgres/schema_inference.py
graflo/db/postgres/types.py
graflo/db/postgres/util.py
graflo/db/tigergraph/__init__.py
graflo/db/tigergraph/conn.py
graflo/db/tigergraph/onto.py
graflo/db/tigergraph/reserved_words.json
graflo/filter/__init__.py
graflo/filter/onto.py
graflo/plot/__init__.py
graflo/plot/plotter.py
graflo/util/__init__.py
graflo/util/chunker.py
graflo/util/merge.py
graflo/util/misc.py
graflo/util/onto.py
graflo/util/transform.py
graflo-1.4.0.dist-info/METADATA
graflo-1.4.0.dist-info/WHEEL
graflo-1.4.0.dist-info/entry_points.txt
graflo-1.4.0.dist-info/licenses/LICENSE
graflo-1.4.0.dist-info/RECORD
