Metadata-Version: 2.4
Name: graflo
Version: 1.4.0
Summary: A framework for transforming tabular (CSV, SQL) and hierarchical data (JSON, XML) into property graphs and ingesting them into graph databases (ArangoDB, Neo4j, TigerGraph). Features automatic PostgreSQL schema inference.
Author-email: Alexander Belikov <alexander@growgraph.dev>
License-File: LICENSE
Classifier: Programming Language :: Python :: 3
Classifier: Programming Language :: Python :: 3.11
Classifier: Programming Language :: Python :: 3.12
Classifier: Programming Language :: Python :: Implementation :: CPython
Requires-Python: >=3.11
Requires-Dist: click<9,>=8.2.0
Requires-Dist: dataclass-wizard>=0.34.0
Requires-Dist: falkordb>=1.0.9
Requires-Dist: ijson<4,>=3.2.3
Requires-Dist: neo4j<6,>=5.22.0
Requires-Dist: networkx~=3.3
Requires-Dist: pandas-stubs==2.3.0.250703
Requires-Dist: pandas<3,>=2.0.3
Requires-Dist: psycopg2-binary>=2.9.11
Requires-Dist: pydantic-settings>=2.12.0
Requires-Dist: pydantic>=2.12.5
Requires-Dist: pymgclient>=1.3.1
Requires-Dist: python-arango<9,>=8.1.2
Requires-Dist: redis>=5.0.0
Requires-Dist: requests>=2.31.0
Requires-Dist: sqlalchemy>=2.0.0
Requires-Dist: strenum>=0.4.15
Requires-Dist: suthing>=0.5.0
Requires-Dist: urllib3>=2.0.0
Requires-Dist: xmltodict<0.15,>=0.14.2
Provides-Extra: plot
Requires-Dist: pygraphviz>=1.14; extra == 'plot'
